{"files":{"packages/frontend/dist/assets/index-_ZRWu3s7.js.map":{"size":4588713,"mtime_nanos":1782025533541281590,"mode":420,"is_dir":false},"packages/frontend/dist/index.html":{"size":2512,"mtime_nanos":1782025533540394323,"mode":420,"is_dir":false},"packages/frontend/dist":{"size":0,"mtime_nanos":0,"mode":0,"is_dir":true},"packages/frontend/dist/assets":{"size":0,"mtime_nanos":0,"mode":0,"is_dir":true},"packages/frontend/.turbo/turbo-build.log":{"size":793,"mtime_nanos":1782025533622270850,"mode":420,"is_dir":false},"packages/frontend/dist/assets/index-DDbWXICv.css":{"size":31900,"mtime_nanos":1782025533540354405,"mode":420,"is_dir":false},"packages/frontend/dist/assets/index-_ZRWu3s7.js":{"size":976100,"mtime_nanos":1782025533540588410,"mode":420,"is_dir":false}},"order":["packages/frontend/.turbo/turbo-build.log","packages/frontend/dist","packages/frontend/dist/assets","packages/frontend/dist/assets/index-DDbWXICv.css","packages/frontend/dist/assets/index-_ZRWu3s7.js","packages/frontend/dist/assets/index-_ZRWu3s7.js.map","packages/frontend/dist/index.html"]}